sidemash-sdk/__init__.py
sidemash_sdk/Auth.py
sidemash_sdk/Client.py
sidemash_sdk/CreateStreamSquareForm.py
sidemash_sdk/Hook.py
sidemash_sdk/Http.py
sidemash_sdk/HttpCallError.py
sidemash_sdk/HttpMethod.py
sidemash_sdk/InstanceStatus.py
sidemash_sdk/ListForm.py
sidemash_sdk/Pagination.py
sidemash_sdk/Play.py
sidemash_sdk/Publish.py
sidemash_sdk/PublishRtmp.py
sidemash_sdk/RestCollection.py
sidemash_sdk/Sdk.py
sidemash_sdk/SdmRequest.py
sidemash_sdk/SecureAndNonSecure.py
sidemash_sdk/SidemashClient.py
sidemash_sdk/StreamMetaData.py
sidemash_sdk/StreamSquare.py
sidemash_sdk/StreamSquareService.py
sidemash_sdk/StreamSquareSize.py
sidemash_sdk/Timestamp.py
sidemash_sdk/UTCDateTime.py
sidemash_sdk/UpdateStreamSquareForm.py
sidemash_sdk/UserDesc.py
sidemash_sdk/__init__.py
sidemash_sdk/sum.py
sidemash_sdk/example/__init__.py
sidemash_sdk/example/example.py
sidemash_sdk-1.0.7.dist-info/LICENSE
sidemash_sdk-1.0.7.dist-info/METADATA
sidemash_sdk-1.0.7.dist-info/WHEEL
sidemash_sdk-1.0.7.dist-info/top_level.txt
sidemash_sdk-1.0.7.dist-info/RECORD
